koios_python/__init__.py
koios_python/account.py
koios_python/address.py
koios_python/asset.py
koios_python/block.py
koios_python/environment.py
koios_python/epoch.py
koios_python/network.py
koios_python/ogmios.py
koios_python/pool.py
koios_python/scripts.py
koios_python/transactions.py
koios_python/urls.py
koios_python-2.0.0.dist-info/LICENSE.md
koios_python-2.0.0.dist-info/METADATA
koios_python-2.0.0.dist-info/WHEEL
koios_python-2.0.0.dist-info/top_level.txt
koios_python-2.0.0.dist-info/RECORD
