Metadata-Version: 2.1
Name: koios-python
Version: 2.0.0
Summary: Python wrapper Library using Koios API for accessing information stored on the Cardano Blockchain
Home-page: https://github.com/QuixoteSystems
Author: Quixote Stake Pool
Author-email: quixotepool@proton.me
License: MIT
Keywords: koios,blockchain,cardano,API,REST,RESTful
Classifier: Development Status :: 4 - Beta
Classifier: Intended Audience :: Developers
Classifier: Topic :: Software Development :: Build Tools
Classifier: License :: OSI Approved :: MIT License
Classifier: Programming Language :: Python :: 3.8
Classifier: Programming Language :: Python :: 3.9
Classifier: Programming Language :: Python :: 3.10
Classifier: Programming Language :: Python :: 3.11
Classifier: Programming Language :: Python :: 3 :: Only
License-File: LICENSE.md
